{
  "characters": [
    {
      "id": 1,
      "name": "Mr. Cute",
      "image": "https://media.giphy.com/media/v1.Y2lkPTc5MGI3NjExbmYyZGVuYWp0aWdzeG42ZXBjZHg0Z2lhOXBhbmlseDNpMjZ5eDFldCZlcD12MV9naWZzX3NlYXJjaCZjdD1n/MDJ9IbxxvDUQM/giphy.gif",
      "votes": 0
    },
    {
      "id": 2,
      "name": "Mx. Monkey",
      "image": "https://media.giphy.com/media/qixJFUXq1UNLa/giphy.gif?cid=790b76110r0yy6pcdhobyo5ucwpl2r4a8z13lycna9etb59e&ep=v1_gifs_search&rid=giphy.gif&ct=g",
      "votes": 0
    },
    {
      "id": 3,
      "name": "Ms. Zebra",
      "image": "https://media.giphy.com/media/l2YWD4izd8i4zyJWw/giphy.gif?cid=790b76114vu07rxsqo7wjgdbrofje3tmhgqkome3vlshzb4h&ep=v1_gifs_search&rid=giphy.gif&ct=g",
      "votes": 0
    },
    {
      "id": 4,
      "name": "Dr. Lion",
      "image": "https://media.giphy.com/media/ZkBcyGcNwNUUU/giphy.gif?cid=790b7611r4lliexetp3pizxa9k2msjp43xu9wlxsg7epsxgj&ep=v1_gifs_search&rid=giphy.gif&ct=g",
      "votes": 0
    },
    {
      "id": 5,
      "name": "Mme. Panda",
      "image": "https://media.giphy.com/media/xkhn6Ry4taRtC/giphy.gif?cid=790b7611dk26uwp80dhqd1fqshfqo98dooq64074sbt8ptk8&ep=v1_gifs_search&rid=giphy.gif&ct=g",
      "votes": 0
    }
  ]
}
